isovar/__init__.py
isovar/alignment_score.py
isovar/allele_read.py
isovar/allele_read_helpers.py
isovar/assembly.py
isovar/common.py
isovar/dataframe_builder.py
isovar/dataframe_helpers.py
isovar/default_parameters.py
isovar/dna.py
isovar/effect_prediction.py
isovar/filtering.py
isovar/genetic_code.py
isovar/isovar_result.py
isovar/locus_read.py
isovar/logging.conf
isovar/logging.py
isovar/main.py
isovar/phasing.py
isovar/protein_sequence.py
isovar/protein_sequence_creator.py
isovar/protein_sequence_helpers.py
isovar/read_collector.py
isovar/read_evidence.py
isovar/reference_coding_sequence_key.py
isovar/reference_context.py
isovar/reference_context_helpers.py
isovar/reference_sequence_key.py
isovar/string_helpers.py
isovar/translation.py
isovar/translation_helpers.py
isovar/translation_key.py
isovar/value_object.py
isovar/variant_helpers.py
isovar/variant_orf.py
isovar/variant_orf_helpers.py
isovar/variant_sequence.py
isovar/variant_sequence_creator.py
isovar/variant_sequence_helpers.py
isovar/cli/__init__.py
isovar/cli/filter_args.py
isovar/cli/isovar_allele_counts.py
isovar/cli/isovar_allele_reads.py
isovar/cli/isovar_main.py
isovar/cli/isovar_protein_sequences.py
isovar/cli/isovar_reference_contexts.py
isovar/cli/isovar_translations.py
isovar/cli/isovar_variant_reads.py
isovar/cli/isovar_variant_sequences.py
isovar/cli/main_args.py
isovar/cli/output_args.py
isovar/cli/protein_sequence_args.py
isovar/cli/reference_context_args.py
isovar/cli/rna_args.py
isovar/cli/translation_args.py
isovar/cli/variant_sequences_args.py
isovar-1.3.0.dist-info/LICENSE
isovar-1.3.0.dist-info/METADATA
isovar-1.3.0.dist-info/WHEEL
isovar-1.3.0.dist-info/entry_points.txt
isovar-1.3.0.dist-info/top_level.txt
isovar-1.3.0.dist-info/RECORD
