Metadata-Version: 2.1
Name: isovar
Version: 1.3.0
Summary: Determine mutant protein sequences from RN using assembly around variants
Home-page: https://github.com/openvax/isovar
Author: Alex Rubinsteyn, Arman Aksoy, Julia Kodysh
Author-email: alex.rubinsteyn@mssm.edu
License: http://www.apache.org/licenses/LICENSE-2.0.html
Classifier: Development Status :: 4 - Beta
Classifier: Environment :: Console
Classifier: Operating System :: OS Independent
Classifier: Intended Audience :: Science/Research
Classifier: License :: OSI Approved :: Apache Software License
Classifier: Programming Language :: Python
Classifier: Topic :: Scientific/Engineering :: Bio-Informatics
License-File: LICENSE
Requires-Dist: six
Requires-Dist: pysam (>=0.15.2)
Requires-Dist: pandas
Requires-Dist: varcode (>=0.9.0)
Requires-Dist: pyensembl (>=1.5.0)
Requires-Dist: cached-property (>=1.5.1)
Requires-Dist: psutil
